README.rst
setup.py
microforms/__init__.py
microforms/fields.py
microforms/forms.py
microforms/tests.py
microforms.egg-info/PKG-INFO
microforms.egg-info/SOURCES.txt
microforms.egg-info/dependency_links.txt
microforms.egg-info/top_level.txt
micromodels/__init__.py
micromodels/fields.py
micromodels/models.py