Metadata-Version: 1.1
Name: microforms
Version: 0.0.2
Summary: WTForms for micromodels
Home-page: https://github.com/zbyte64/micromodels-forms/
Author: UNKNOWN
Author-email: UNKNOWN
License: Public Domain
Platform: UNKNOWN
Classifier: Programming Language :: Python
Classifier: Development Status :: 3 - Alpha
Classifier: Intended Audience :: Developers
Classifier: License :: Public Domain
Classifier: Operating System :: OS Independent
Classifier: Topic :: Software Development :: Libraries :: Python Modules
